pycdstar3/__init__.py
pycdstar3/__main__.py
pycdstar3/_utils.py
pycdstar3/api.py
pycdstar3/model.py
pycdstar3/cli/__init__.py
pycdstar3/cli/_utils.py
pycdstar3/cli/context.py
pycdstar3/cli/commands/__init__.py
pycdstar3/cli/commands/acl.py
pycdstar3/cli/commands/get.py
pycdstar3/cli/commands/init.py
pycdstar3/cli/commands/ls.py
pycdstar3/cli/commands/meta.py
pycdstar3/cli/commands/profile.py
pycdstar3/cli/commands/put.py
pycdstar3/cli/commands/rm.py
pycdstar3/cli/commands/rma.py
pycdstar3/cli/commands/scroll.py
pycdstar3/cli/commands/search.py
pycdstar3-3.1.0.dist-info/METADATA
pycdstar3-3.1.0.dist-info/WHEEL
pycdstar3-3.1.0.dist-info/entry_points.txt
pycdstar3-3.1.0.dist-info/licenses/LICENSE.txt
pycdstar3-3.1.0.dist-info/RECORD
