Metadata-Version: 2.3
Name: pycdstar3
Version: 3.1.0
Summary: Library and command-line client to access CDSTAR (3.0+)
Project-URL: Homepage, https://gitlab-ce.gwdg.de/cdstar/pycdstar3
Author-email: Marcel Hellkamp <marc@gsites.de>
License: Copyright 2019 Marcel Hellkamp
License-File: LICENSE.txt
Classifier: Development Status :: 6 - Mature
Classifier: Intended Audience :: Developers
Classifier: License :: OSI Approved :: Apache Software License
Classifier: Operating System :: OS Independent
Classifier: Programming Language :: Python :: 3
Requires-Python: >=3.5
Requires-Dist: iso8601
Requires-Dist: requests
Requires-Dist: requests-toolbelt
Requires-Dist: tabulate
Requires-Dist: tqdm
Provides-Extra: dev
Requires-Dist: black; extra == 'dev'
Requires-Dist: flake8; extra == 'dev'
Requires-Dist: hatch; extra == 'dev'
Requires-Dist: tox; extra == 'dev'
Requires-Dist: twine; extra == 'dev'
Requires-Dist: wheel; extra == 'dev'
Provides-Extra: docs
Requires-Dist: sphinx; extra == 'docs'
Provides-Extra: test
Requires-Dist: coverage; extra == 'test'
Requires-Dist: mock; extra == 'test'
Requires-Dist: pytest; extra == 'test'
Requires-Dist: pytest-cov; extra == 'test'
Requires-Dist: responses; extra == 'test'
